hikyuu/LICENSE.txt
hikyuu/__init__.py
hikyuu/__init__.pyi
hikyuu/core.py
hikyuu/core.pyi
hikyuu/extend.py
hikyuu/extend.pyi
hikyuu/hub.py
hikyuu/hub.pyi
hikyuu/interactive.py
hikyuu/analysis/__init__.py
hikyuu/analysis/__init__.pyi
hikyuu/analysis/analysis.py
hikyuu/analysis/analysis.pyi
hikyuu/config/__init__.py
hikyuu/config/block/__init__.py
hikyuu/config/block/dybk.ini
hikyuu/config/block/gnbk.ini
hikyuu/config/block/hybk.ini
hikyuu/config/block/self.ini
hikyuu/config/block/zsbk.ini
hikyuu/cpp/__init__.py
hikyuu/cpp/__init__.pyi
hikyuu/cpp/core310.pyi
hikyuu/cpp/core310.so
hikyuu/cpp/core311.pyi
hikyuu/cpp/core311.so
hikyuu/cpp/core312.pyi
hikyuu/cpp/core312.so
hikyuu/cpp/core313.pyi
hikyuu/cpp/core313.so
hikyuu/cpp/libboost_atomic.so
hikyuu/cpp/libboost_atomic.so.1.90.0
hikyuu/cpp/libboost_charconv.so
hikyuu/cpp/libboost_charconv.so.1.90.0
hikyuu/cpp/libboost_chrono.so
hikyuu/cpp/libboost_chrono.so.1.90.0
hikyuu/cpp/libboost_container.so
hikyuu/cpp/libboost_container.so.1.90.0
hikyuu/cpp/libboost_date_time.so
hikyuu/cpp/libboost_date_time.so.1.90.0
hikyuu/cpp/libboost_locale.so
hikyuu/cpp/libboost_locale.so.1.90.0
hikyuu/cpp/libboost_random.so
hikyuu/cpp/libboost_random.so.1.90.0
hikyuu/cpp/libboost_serialization.so
hikyuu/cpp/libboost_serialization.so.1.90.0
hikyuu/cpp/libboost_thread.so
hikyuu/cpp/libboost_thread.so.1.90.0
hikyuu/cpp/libboost_wserialization.so
hikyuu/cpp/libboost_wserialization.so.1.90.0
hikyuu/cpp/libcrypto.so.3
hikyuu/cpp/libhikyuu.so
hikyuu/cpp/libhku_hdf5.so
hikyuu/cpp/libhku_hdf5.so.200
hikyuu/cpp/libhku_hdf5.so.200.2.0
hikyuu/cpp/libhku_hdf5_cpp.so
hikyuu/cpp/libhku_hdf5_cpp.so.200
hikyuu/cpp/libhku_hdf5_cpp.so.200.2.0
hikyuu/cpp/libhku_hdf5_hl.so
hikyuu/cpp/libhku_hdf5_hl.so.200
hikyuu/cpp/libhku_hdf5_hl.so.200.1.0
hikyuu/cpp/libhku_hdf5_hl_cpp.so
hikyuu/cpp/libhku_hdf5_hl_cpp.so.200
hikyuu/cpp/libhku_hdf5_hl_cpp.so.200.1.0
hikyuu/cpp/libhku_hdf5_tools.so
hikyuu/cpp/libhku_hdf5_tools.so.200
hikyuu/cpp/libhku_hdf5_tools.so.200.1.1
hikyuu-2.7.3.dist-info/METADATA
hikyuu-2.7.3.dist-info/WHEEL
hikyuu-2.7.3.dist-info/entry_points.txt
hikyuu-2.7.3.dist-info/top_level.txt
hikyuu-2.7.3.dist-info/RECORD
